{"data":{"allMarkdownRemark":{"group":[{"fieldValue":"1 Corinthians","totalCount":1},{"fieldValue":"Anxiety","totalCount":3},{"fieldValue":"Blessed","totalCount":1},{"fieldValue":"Devotional","totalCount":5},{"fieldValue":"Faith","totalCount":1},{"fieldValue":"Fear","totalCount":1},{"fieldValue":"Flesh","totalCount":2},{"fieldValue":"Humble","totalCount":1},{"fieldValue":"Matthew","totalCount":1},{"fieldValue":"Prayer","totalCount":1},{"fieldValue":"Proverbs","totalCount":2},{"fieldValue":"Psalm","totalCount":1},{"fieldValue":"Psalms","totalCount":1},{"fieldValue":"Refuge","totalCount":1},{"fieldValue":"Sermon Notes","totalCount":1},{"fieldValue":"Sin","totalCount":1},{"fieldValue":"Spiritual Warfare","totalCount":1},{"fieldValue":"Temptation","totalCount":1},{"fieldValue":"Victory","totalCount":2},{"fieldValue":"Worry","totalCount":3}]}}}